setup.py
wayround_org/getthesource/commands.py
wayround_org/getthesource/git_tool.py
wayround_org/getthesource/main.py
wayround_org/getthesource/mirrorer.py
wayround_org/getthesource/openjdk_downloader.py
wayround_org/getthesource/repo_worker.py
wayround_org/getthesource/uriexplorer.py
wayround_org/getthesource/modules/__init__.py
wayround_org/getthesource/modules/downloaders/__init__.py
wayround_org/getthesource/modules/downloaders/wget.py
wayround_org/getthesource/modules/providers/__init__.py
wayround_org/getthesource/modules/providers/gnome_org.py
wayround_org/getthesource/modules/providers/gnu_org.py
wayround_org/getthesource/modules/providers/kernel_org.py
wayround_org/getthesource/modules/providers/launchpad_net.py
wayround_org/getthesource/modules/providers/sourceforge_net.py
wayround_org/getthesource/modules/providers/std_simple.py
wayround_org/getthesource/modules/providers/templates/__init__.py
wayround_org/getthesource/modules/providers/templates/std_https.py
wayround_org_getthesource.egg-info/PKG-INFO
wayround_org_getthesource.egg-info/SOURCES.txt
wayround_org_getthesource.egg-info/dependency_links.txt
wayround_org_getthesource.egg-info/entry_points.txt
wayround_org_getthesource.egg-info/requires.txt
wayround_org_getthesource.egg-info/top_level.txt