Metadata-Version: 1.1
Name: wayround-org-getthesource
Version: 0.2.9
Summary: modular tool for downloading lates N (by version numbering) tarballs from given site
Home-page: https://github.com/AnimusPEXUS/wayround_org_getthesource
Author: Alexey Gorshkov
Author-email: animus@wayround.org
License: UNKNOWN
Platform: UNKNOWN
Classifier: License :: OSI Approved :: GNU General Public License v3 or later (GPLv3+)
